sgr_ansi/__init__.py
sgr_ansi/_chain.py
sgr_ansi/ansi8.py
sgr_ansi/demo.py
sgr_ansi-0.0.5.dist-info/LICENSE
sgr_ansi-0.0.5.dist-info/METADATA
sgr_ansi-0.0.5.dist-info/WHEEL
sgr_ansi-0.0.5.dist-info/entry_points.txt
sgr_ansi-0.0.5.dist-info/top_level.txt
sgr_ansi-0.0.5.dist-info/RECORD
