Metadata-Version: 2.1
Name: sgr-ansi
Version: 0.0.5
Summary: awesome ansi8 colorful text interface in terminal
Home-page: https://github.com/coghost/sgr-ansi
Author: lihe
Author-email: imanux@sina.com
License: GPL
Project-URL: Bug Reports, https://github.com/coghost/sgr-ansi/issues
Project-URL: Source, https://github.com/coghost/sgr-ansi
Keywords: sgr,ansi,colorful,vivid,awesome,terminal
Platform: UNKNOWN
Classifier: Programming Language :: Python :: 3.7
Classifier: Programming Language :: Python :: 3.8
Requires-Python: >=3.7
